<?xml version="1.0" encoding="gb2312" ?>
<StockCodeMain xmlns="http://www.fd911.net" version="1.00">
    <StockCodes>
		<StockCode code="SH000001" name="上证指数" dayfilepath="" minfilepath=""/>
		<StockCode code="SH000016" name="上证50" dayfilepath="" minfilepath=""/>
		<StockCode code="SH000300" name="沪深300" dayfilepath="" minfilepath=""/>
		<StockCode code="SZ399006" name="创业板指" dayfilepath="" minfilepath=""/>
        <StockCode code="SH880301" name="煤炭" dayfilepath="" minfilepath="" />
        <StockCode code="SH880302" name="煤炭开采" dayfilepath="" minfilepath="" />
        <StockCode code="SH880303" name="焦炭加工" dayfilepath="" minfilepath="" />
        <StockCode code="SH880305" name="电力" dayfilepath="" minfilepath="" />
        <StockCode code="SH880306" name="水力发电" dayfilepath="" minfilepath="" />
        <StockCode code="SH880307" name="火力发电" dayfilepath="" minfilepath="" />
        <StockCode code="SH880308" name="新型电力" dayfilepath="" minfilepath="" />
        <StockCode code="SH880310" name="石油" dayfilepath="" minfilepath="" />
        <StockCode code="SH880311" name="石油开采" dayfilepath="" minfilepath="" />
        <StockCode code="SH880312" name="石油加工" dayfilepath="" minfilepath="" />
        <StockCode code="SH880313" name="石油贸易" dayfilepath="" minfilepath="" />
        <StockCode code="SH880318" name="钢铁" dayfilepath="" minfilepath="" />
        <StockCode code="SH880319" name="普钢" dayfilepath="" minfilepath="" />
        <StockCode code="SH880320" name="特种钢" dayfilepath="" minfilepath="" />
        <StockCode code="SH880321" name="钢加工" dayfilepath="" minfilepath="" />
        <StockCode code="SH880324" name="有色" dayfilepath="" minfilepath="" />
        <StockCode code="SH880325" name="铜" dayfilepath="" minfilepath="" />
        <StockCode code="SH880326" name="铝" dayfilepath="" minfilepath="" />
        <StockCode code="SH880327" name="铅锌" dayfilepath="" minfilepath="" />
        <StockCode code="SH880328" name="黄金" dayfilepath="" minfilepath="" />
        <StockCode code="SH880329" name="小金属" dayfilepath="" minfilepath="" />
        <StockCode code="SH880330" name="化纤" dayfilepath="" minfilepath="" />
        <StockCode code="SH880335" name="化工" dayfilepath="" minfilepath="" />
        <StockCode code="SH880336" name="化工原料" dayfilepath="" minfilepath="" />
        <StockCode code="SH880337" name="农药化肥" dayfilepath="" minfilepath="" />
        <StockCode code="SH880338" name="塑料" dayfilepath="" minfilepath="" />
        <StockCode code="SH880339" name="橡胶" dayfilepath="" minfilepath="" />
        <StockCode code="SH880340" name="染料涂料" dayfilepath="" minfilepath="" />
        <StockCode code="SH880344" name="建材" dayfilepath="" minfilepath="" />
        <StockCode code="SH880345" name="陶瓷" dayfilepath="" minfilepath="" />
        <StockCode code="SH880346" name="水泥" dayfilepath="" minfilepath="" />
        <StockCode code="SH880347" name="玻璃" dayfilepath="" minfilepath="" />
        <StockCode code="SH880348" name="其他建材" dayfilepath="" minfilepath="" />
        <StockCode code="SH880350" name="造纸" dayfilepath="" minfilepath="" />
        <StockCode code="SH880351" name="矿物制品" dayfilepath="" minfilepath="" />
        <StockCode code="SH880355" name="日用化工" dayfilepath="" minfilepath="" />
        <StockCode code="SH880360" name="农林牧渔" dayfilepath="" minfilepath="" />
        <StockCode code="SH880361" name="种植业" dayfilepath="" minfilepath="" />
        <StockCode code="SH880362" name="渔业" dayfilepath="" minfilepath="" />
        <StockCode code="SH880363" name="林业" dayfilepath="" minfilepath="" />
        <StockCode code="SH880364" name="饲料" dayfilepath="" minfilepath="" />
        <StockCode code="SH880366" name="农业综合" dayfilepath="" minfilepath="" />
        <StockCode code="SH880367" name="纺织服饰" dayfilepath="" minfilepath="" />
        <StockCode code="SH880368" name="纺织" dayfilepath="" minfilepath="" />
        <StockCode code="SH880369" name="服饰" dayfilepath="" minfilepath="" />
        <StockCode code="SH880372" name="食品饮料" dayfilepath="" minfilepath="" />
        <StockCode code="SH880373" name="乳制品" dayfilepath="" minfilepath="" />
        <StockCode code="SH880374" name="软饮料" dayfilepath="" minfilepath="" />
        <StockCode code="SH880375" name="食品" dayfilepath="" minfilepath="" />
        <StockCode code="SH880380" name="酿酒" dayfilepath="" minfilepath="" />
        <StockCode code="SH880381" name="白酒" dayfilepath="" minfilepath="" />
        <StockCode code="SH880382" name="啤酒" dayfilepath="" minfilepath="" />
        <StockCode code="SH880383" name="红黄酒" dayfilepath="" minfilepath="" />
        <StockCode code="SH880387" name="家用电器" dayfilepath="" minfilepath="" />
        <StockCode code="SH880390" name="汽车类" dayfilepath="" minfilepath="" />
        <StockCode code="SH880391" name="汽车整车" dayfilepath="" minfilepath="" />
        <StockCode code="SH880392" name="汽车配件" dayfilepath="" minfilepath="" />
        <StockCode code="SH880393" name="汽车服务" dayfilepath="" minfilepath="" />
        <StockCode code="SH880394" name="摩托车" dayfilepath="" minfilepath="" />
        <StockCode code="SH880398" name="医疗保健" dayfilepath="" minfilepath="" />
        <StockCode code="SH880399" name="家居用品" dayfilepath="" minfilepath="" />
        <StockCode code="SH880400" name="医药" dayfilepath="" minfilepath="" />
        <StockCode code="SH880401" name="化学制药" dayfilepath="" minfilepath="" />
        <StockCode code="SH880402" name="生物制药" dayfilepath="" minfilepath="" />
        <StockCode code="SH880403" name="中成药" dayfilepath="" minfilepath="" />
        <StockCode code="SH880406" name="商业连锁" dayfilepath="" minfilepath="" />
        <StockCode code="SH880407" name="百货" dayfilepath="" minfilepath="" />
        <StockCode code="SH880408" name="超市连锁" dayfilepath="" minfilepath="" />
        <StockCode code="SH880409" name="电器连锁" dayfilepath="" minfilepath="" />
        <StockCode code="SH880410" name="医药商业" dayfilepath="" minfilepath="" />
        <StockCode code="SH880411" name="其他商业" dayfilepath="" minfilepath="" />
        <StockCode code="SH880412" name="商品城" dayfilepath="" minfilepath="" />
        <StockCode code="SH880413" name="批发业" dayfilepath="" minfilepath="" />
        <StockCode code="SH880414" name="商贸代理" dayfilepath="" minfilepath="" />
        <StockCode code="SH880418" name="传媒娱乐" dayfilepath="" minfilepath="" />
        <StockCode code="SH880419" name="出版业" dayfilepath="" minfilepath="" />
        <StockCode code="SH880420" name="影视音像" dayfilepath="" minfilepath="" />
        <StockCode code="SH880421" name="广告包装" dayfilepath="" minfilepath="" />
        <StockCode code="SH880422" name="文教休闲" dayfilepath="" minfilepath="" />
        <StockCode code="SH880423" name="酒店餐饮" dayfilepath="" minfilepath="" />
        <StockCode code="SH880424" name="旅游" dayfilepath="" minfilepath="" />
        <StockCode code="SH880425" name="旅游服务" dayfilepath="" minfilepath="" />
        <StockCode code="SH880426" name="旅游景点" dayfilepath="" minfilepath="" />
        <StockCode code="SH880430" name="航空" dayfilepath="" minfilepath="" />
        <StockCode code="SH880431" name="船舶" dayfilepath="" minfilepath="" />
        <StockCode code="SH880432" name="运输设备" dayfilepath="" minfilepath="" />
        <StockCode code="SH880437" name="通用机械" dayfilepath="" minfilepath="" />
        <StockCode code="SH880438" name="机床制造" dayfilepath="" minfilepath="" />
        <StockCode code="SH880439" name="机械基件" dayfilepath="" minfilepath="" />
        <StockCode code="SH880440" name="工业机械" dayfilepath="" minfilepath="" />
        <StockCode code="SH880441" name="化工机械" dayfilepath="" minfilepath="" />
        <StockCode code="SH880442" name="轻工机械" dayfilepath="" minfilepath="" />
        <StockCode code="SH880443" name="纺织机械" dayfilepath="" minfilepath="" />
        <StockCode code="SH880444" name="农用机械" dayfilepath="" minfilepath="" />
        <StockCode code="SH880445" name="专用机械" dayfilepath="" minfilepath="" />
        <StockCode code="SH880446" name="电气设备" dayfilepath="" minfilepath="" />
        <StockCode code="SH880447" name="工程机械" dayfilepath="" minfilepath="" />
        <StockCode code="SH880448" name="电器仪表" dayfilepath="" minfilepath="" />
        <StockCode code="SH880452" name="电信运营" dayfilepath="" minfilepath="" />
        <StockCode code="SH880453" name="公共交通" dayfilepath="" minfilepath="" />
        <StockCode code="SH880454" name="水务" dayfilepath="" minfilepath="" />
        <StockCode code="SH880455" name="供气供热" dayfilepath="" minfilepath="" />
        <StockCode code="SH880456" name="环境保护" dayfilepath="" minfilepath="" />
        <StockCode code="SH880459" name="运输服务" dayfilepath="" minfilepath="" />
        <StockCode code="SH880460" name="铁路" dayfilepath="" minfilepath="" />
        <StockCode code="SH880461" name="水运" dayfilepath="" minfilepath="" />
        <StockCode code="SH880462" name="空运" dayfilepath="" minfilepath="" />
        <StockCode code="SH880463" name="公路" dayfilepath="" minfilepath="" />
        <StockCode code="SH880464" name="仓储物流" dayfilepath="" minfilepath="" />
        <StockCode code="SH880465" name="交通设施" dayfilepath="" minfilepath="" />
        <StockCode code="SH880466" name="路桥" dayfilepath="" minfilepath="" />
        <StockCode code="SH880467" name="机场" dayfilepath="" minfilepath="" />
        <StockCode code="SH880468" name="港口" dayfilepath="" minfilepath="" />
        <StockCode code="SH880471" name="银行" dayfilepath="" minfilepath="" />
        <StockCode code="SH880472" name="证券" dayfilepath="" minfilepath="" />
        <StockCode code="SH880473" name="保险" dayfilepath="" minfilepath="" />
        <StockCode code="SH880474" name="多元金融" dayfilepath="" minfilepath="" />
        <StockCode code="SH880476" name="建筑" dayfilepath="" minfilepath="" />
        <StockCode code="SH880477" name="建筑工程" dayfilepath="" minfilepath="" />
        <StockCode code="SH880478" name="装修装饰" dayfilepath="" minfilepath="" />
        <StockCode code="SH880482" name="房地产" dayfilepath="" minfilepath="" />
        <StockCode code="SH880483" name="全国地产" dayfilepath="" minfilepath="" />
        <StockCode code="SH880484" name="区域地产" dayfilepath="" minfilepath="" />
        <StockCode code="SH880485" name="园区开发" dayfilepath="" minfilepath="" />
        <StockCode code="SH880486" name="房产服务" dayfilepath="" minfilepath="" />
        <StockCode code="SH880489" name="IT设备" dayfilepath="" minfilepath="" />
        <StockCode code="SH880490" name="通信设备" dayfilepath="" minfilepath="" />
        <StockCode code="SH880491" name="半导体" dayfilepath="" minfilepath="" />
        <StockCode code="SH880492" name="元器件" dayfilepath="" minfilepath="" />
        <StockCode code="SH880493" name="软件服务" dayfilepath="" minfilepath="" />
        <StockCode code="SH880494" name="互联网" dayfilepath="" minfilepath="" />
        <StockCode code="SH880497" name="综合类" dayfilepath="" minfilepath="" />
    </StockCodes>
</StockCodeMain>
